aws_knowledge_tool/__init__.py
aws_knowledge_tool/cli.py
aws_knowledge_tool/logging_config.py
aws_knowledge_tool/utils.py
aws_knowledge_tool/commands/__init__.py
aws_knowledge_tool/commands/completion.py
aws_knowledge_tool/commands/read.py
aws_knowledge_tool/commands/recommend.py
aws_knowledge_tool/commands/search.py
aws_knowledge_tool/core/__init__.py
aws_knowledge_tool/core/exceptions.py
aws_knowledge_tool/core/mcp_client.py
aws_knowledge_tool-0.1.0.dist-info/METADATA
aws_knowledge_tool-0.1.0.dist-info/WHEEL
aws_knowledge_tool-0.1.0.dist-info/entry_points.txt
aws_knowledge_tool-0.1.0.dist-info/licenses/LICENSE
aws_knowledge_tool-0.1.0.dist-info/RECORD
