Metadata-Version: 2.4
Name: aws-knowledge-tool
Version: 0.1.0
Summary: CLI tool for querying AWS Knowledge MCP Server - search, read, and discover AWS documentation
Project-URL: Homepage, https://github.com/dnvriend/aws-knowledge-tool
Project-URL: Repository, https://github.com/dnvriend/aws-knowledge-tool
Project-URL: Issues, https://github.com/dnvriend/aws-knowledge-tool/issues
Author-email: Dennis Vriend <dvriend@ilionx.com>
License: MIT
License-File: LICENSE
Keywords: aws,aws-docs,cli,documentation,knowledge-base,mcp-server,search
Classifier: Development Status :: 4 - Beta
Classifier: Intended Audience :: Developers
Classifier: Intended Audience :: System Administrators
Classifier: License :: OSI Approved :: MIT License
Classifier: Programming Language :: Python :: 3
Classifier: Programming Language :: Python :: 3.14
Classifier: Topic :: Documentation
Classifier: Topic :: Software Development :: Documentation
Classifier: Topic :: System :: Systems Administration
Classifier: Topic :: Utilities
Requires-Python: >=3.14
Requires-Dist: click>=8.1.7
Requires-Dist: requests>=2.31.0
